ngdataqualitycheck/__init__.py
ngdataqualitycheck/data_quality.py
ngdataqualitycheck/data_stats.py
ngdataqualitycheck/global_params.py
ngdataqualitycheck/helper.py
ngdataqualitycheck/make_directory.py
ngdataqualitycheck/plot_builder.py
ngdataqualitycheck-0.0.1.dist-info/LICENSE
ngdataqualitycheck-0.0.1.dist-info/METADATA
ngdataqualitycheck-0.0.1.dist-info/WHEEL
ngdataqualitycheck-0.0.1.dist-info/top_level.txt
ngdataqualitycheck-0.0.1.dist-info/RECORD
