Metadata-Version: 2.1
Name: ngdataqualitycheck
Version: 0.0.1
Summary: Package for checking data quality.
Home-page: https://github.com/ngenux/ngdataqualitycheck
Download-URL: https://github.com/ngenux/ngdataqualitycheck/archive/refs/tags/0.0.1.tar.gz
Author: Ngenux Solutions Pvt. Ltd.
Author-email: connect@ngenux.com
License: Creative Commons Attribution-NonCommercial-NoDerivatives 4.0 International
Project-URL: Bug Tracker, https://github.com/ngenux/ngdataqualitycheck/issues
Classifier: Development Status :: 3 - Alpha
Classifier: Intended Audience :: Developers
Classifier: Topic :: Software Development :: Documentation
Classifier: License :: OSI Approved :: Common Public License
Classifier: Programming Language :: Python :: 3
Classifier: Programming Language :: Python :: 3.8
License-File: LICENSE
Requires-Dist: numpy
Requires-Dist: pandas
Requires-Dist: python-docx
Requires-Dist: matplotlib
Requires-Dist: seaborn
Requires-Dist: beautifulsoup4
Requires-Dist: wordcloud
Requires-Dist: nltk
Requires-Dist: missingno
